CHANGELOG.txt
LICENCE.txt
MANIFEST.in
README.md
setup.py
ChemLigandSeek/__init__.py
ChemLigandSeek.egg-info/PKG-INFO
ChemLigandSeek.egg-info/SOURCES.txt
ChemLigandSeek.egg-info/dependency_links.txt
ChemLigandSeek.egg-info/requires.txt
ChemLigandSeek.egg-info/top_level.txt