Metadata-Version: 2.1
Name: ChemLigandSeek
Version: 0.0.2
Summary: hemLigandSeek: A Python tool for rapid ligand-based screening, utilizing the PubChem API to identify potential active candidates for bioassays. Filters out compounds violating Lipinski Rule of Five for optimized drug-like properties.
Home-page: https://github.com/ahmed1212212/ChemLigandSeek.git
Author: Ahmed Alhilal
Author-email: aalhilal@udel.edu
License: MIT
Keywords: Cheminformatics
Classifier: Development Status :: 5 - Production/Stable
Classifier: Intended Audience :: Education
Classifier: Operating System :: Microsoft :: Windows :: Windows 10
Classifier: License :: OSI Approved :: MIT License
Classifier: Programming Language :: Python :: 3
License-File: LICENCE.txt
